simpack/arduino.py
simpack/compile.py
simpack/dataprovider.py
simpack/functions.py
simpack/game_base.py
simpack/gui.py
simpack/phisics.py
simpack/request.py
simpack/sockets.py
simpack/soundmgr.py
simpack/_MPH.py
simpack/__init__.py
simpack-1.0.0a1.dist-info/DESCRIPTION.rst
simpack-1.0.0a1.dist-info/entry_points.txt
simpack-1.0.0a1.dist-info/METADATA
simpack-1.0.0a1.dist-info/metadata.json
simpack-1.0.0a1.dist-info/RECORD
simpack-1.0.0a1.dist-info/top_level.txt
simpack-1.0.0a1.dist-info/WHEEL
